napari_buds/__init__.py
napari_buds/_reader.py
napari_buds/_sample_data.py
napari_buds/_segmentation_functions copy.py
napari_buds/_segmentation_functions.py
napari_buds/_testing_working.py
napari_buds/_translate.py
napari_buds/_widget.py
napari_buds/_widget_overview.py
napari_buds/_widgets.py
napari_buds/_writer.py
napari_buds/napari.yaml
napari_buds/open_images.py
napari_buds/_tests/__init__.py
napari_buds/_tests/test_widgets.py
napari_buds-0.1.6.dist-info/LICENSE
napari_buds-0.1.6.dist-info/METADATA
napari_buds-0.1.6.dist-info/WHEEL
napari_buds-0.1.6.dist-info/entry_points.txt
napari_buds-0.1.6.dist-info/top_level.txt
napari_buds-0.1.6.dist-info/RECORD
