Metadata-Version: 2.1
Name: napari-buds
Version: 0.1.6
Summary: Random-forest automated bud annotation
Home-page: https://github.com/SanderSMFISH/napari-buds
Author: Sander van Otterdijk
Author-email: scvanotterdijk@gmail.com
License: BSD-3-Clause
Project-URL: Bug Tracker, https://github.com/SanderSMFISH/napari-buds/issues
Project-URL: Documentation, https://github.com/SanderSMFISH/napari-buds#README.md
Project-URL: Source Code, https://github.com/SanderSMFISH/napari-buds
Project-URL: User Support, https://github.com/SanderSMFISH/napari-buds/issues
Classifier: Development Status :: 2 - Pre-Alpha
Classifier: Framework :: napari
Classifier: Intended Audience :: Developers
Classifier: License :: OSI Approved :: BSD License
Classifier: Operating System :: OS Independent
Classifier: Programming Language :: Python
Classifier: Programming Language :: Python :: 3
Classifier: Programming Language :: Python :: 3 :: Only
Classifier: Programming Language :: Python :: 3.8
Classifier: Programming Language :: Python :: 3.9
Classifier: Programming Language :: Python :: 3.10
Classifier: Topic :: Scientific/Engineering :: Image Processing
Requires-Python: >=3.8
License-File: LICENSE
Requires-Dist: numpy
Requires-Dist: magicgui
Requires-Dist: qtpy
Requires-Dist: pandas
Requires-Dist: napari
Requires-Dist: magic-class
Requires-Dist: scipy
Requires-Dist: scikit-learn
Requires-Dist: scikit-image
Requires-Dist: matplotlib
Requires-Dist: joblib
Requires-Dist: imageio-ffmpeg
Requires-Dist: stackview
Requires-Dist: jupyterlab
Provides-Extra: testing
Requires-Dist: tox ; extra == 'testing'
Requires-Dist: pytest ; extra == 'testing'
Requires-Dist: pytest-cov ; extra == 'testing'
Requires-Dist: pytest-qt ; extra == 'testing'
Requires-Dist: napari ; extra == 'testing'
Requires-Dist: pyqt5 ; extra == 'testing'
